LICENSE
MANIFEST.in
README.rst
setup.cfg
setup.py
django_password_reset_ispm.egg-info/PKG-INFO
django_password_reset_ispm.egg-info/SOURCES.txt
django_password_reset_ispm.egg-info/dependency_links.txt
django_password_reset_ispm.egg-info/not-zip-safe
django_password_reset_ispm.egg-info/requires.txt
django_password_reset_ispm.egg-info/top_level.txt
password_reset/__init__.py
password_reset/forms.py
password_reset/models.py
password_reset/signals.py
password_reset/urls.py
password_reset/utils.py
password_reset/views.py
password_reset/locale/de/LC_MESSAGES/django.mo
password_reset/locale/de/LC_MESSAGES/django.po
password_reset/locale/es/LC_MESSAGES/django.mo
password_reset/locale/es/LC_MESSAGES/django.po
password_reset/locale/fr/LC_MESSAGES/django.mo
password_reset/locale/fr/LC_MESSAGES/django.po
password_reset/locale/ka/LC_MESSAGES/django.mo
password_reset/locale/ka/LC_MESSAGES/django.po
password_reset/locale/nb/LC_MESSAGES/django.mo
password_reset/locale/nb/LC_MESSAGES/django.po
password_reset/locale/pl/LC_MESSAGES/django.mo
password_reset/locale/pl/LC_MESSAGES/django.po
password_reset/locale/pt_BR/LC_MESSAGES/django.mo
password_reset/locale/pt_BR/LC_MESSAGES/django.po
password_reset/locale/ru/LC_MESSAGES/django.mo
password_reset/locale/ru/LC_MESSAGES/django.po
password_reset/locale/zh-hans/LC_MESSAGES/django.mo
password_reset/locale/zh-hans/LC_MESSAGES/django.po
password_reset/templates/password_reset/base.html
password_reset/templates/password_reset/recovery_done.html
password_reset/templates/password_reset/recovery_email.txt
password_reset/templates/password_reset/recovery_email_subject.txt
password_reset/templates/password_reset/recovery_form.html
password_reset/templates/password_reset/reset.html
password_reset/templates/password_reset/reset_sent.html
password_reset/templates/password_reset/reset_sent_failed.html
password_reset/tests/__init__.py
password_reset/tests/models.py
password_reset/tests/settings.py
password_reset/tests/tests.py
password_reset/tests/urls.py
password_reset/tests/views.py