Metadata-Version: 1.1
Name: django-password-reset-ispm
Version: 0.8.2.pre.1
Summary: Class-based views for password reset. ISPM version, captcha merged
Home-page: https://github.com/ISPM/django-password-reset
Author: Bruno Renie
Author-email: bruno@renie.fr
License: BSD licence, see LICENSE file
Download-URL: https://github.com/ISPM/django-password-reset/tarball/0.8.2.pre.1
Platform: UNKNOWN
Classifier: Development Status :: 4 - Beta
Classifier: Environment :: Web Environment
Classifier: Framework :: Django
Classifier: Intended Audience :: Developers
Classifier: License :: OSI Approved :: BSD License
Classifier: Natural Language :: English
Classifier: Programming Language :: Python
Classifier: Programming Language :: Python :: 3
